plico_motor_server/__init__.py
plico_motor_server/__version__.py
plico_motor_server/calib/__init__.py
plico_motor_server/conf/plico_motor_server.conf
plico_motor_server/controller/__init__.py
plico_motor_server/controller/controller.py
plico_motor_server/controller/runner.py
plico_motor_server/devices/FW102B_thorlabs.py
plico_motor_server/devices/KDC101_thorlabs.py
plico_motor_server/devices/KURIOSVB1_thorlabs.py
plico_motor_server/devices/LTS_thorlabs.py
plico_motor_server/devices/MFF10x_thorlabs.py
plico_motor_server/devices/PI_motors.py
plico_motor_server/devices/__init__.py
plico_motor_server/devices/abstract_motor.py
plico_motor_server/devices/fake_newfocus8742.py
plico_motor_server/devices/picomotor.py
plico_motor_server/devices/simulated_motor.py
plico_motor_server/devices/standa_motors.py
plico_motor_server/process_monitor/__init__.py
plico_motor_server/process_monitor/plico_motor_run_process_monitor.py
plico_motor_server/process_monitor/runner.py
plico_motor_server/scripts/__init__.py
plico_motor_server/scripts/controller.py
plico_motor_server/scripts/kill_processes.py
plico_motor_server/scripts/process_monitor.py
plico_motor_server/scripts/stop.py
plico_motor_server/utils/__init__.py
plico_motor_server/utils/constants.py
plico_motor_server/utils/process_startup_helper.py
plico_motor_server/utils/starter_script_creator.py
plico_motor_server-0.1.2.dist-info/LICENSE
plico_motor_server-0.1.2.dist-info/METADATA
plico_motor_server-0.1.2.dist-info/WHEEL
plico_motor_server-0.1.2.dist-info/entry_points.txt
plico_motor_server-0.1.2.dist-info/top_level.txt
plico_motor_server-0.1.2.dist-info/RECORD
