Metadata-Version: 2.1
Name: plico-motor-server
Version: 0.1.2
Summary: motor controller with PLICO
Home-page: https://github.com/ArcetriAdaptiveOptics/plico_motor
Author: Lorenzo Busoni, Alfio Puglisi
Author-email: lorenzo.busoni@inaf.it
License: MIT
Keywords: plico,motor,laboratory,instrumentation control
Classifier: Development Status :: 4 - Beta
Classifier: Operating System :: POSIX :: Linux
Classifier: Programming Language :: Python :: 3
License-File: LICENSE
Requires-Dist: plico >=0.27
Requires-Dist: plico-motor >=0.0.5
Requires-Dist: numpy
Requires-Dist: psutil
Requires-Dist: pyserial
Requires-Dist: pipython
Requires-Dist: libximc
Requires-Dist: pythonnet
